scrapontologies/__init__.py
scrapontologies/db_client.py
scrapontologies/extractor.py
scrapontologies/llm_client.py
scrapontologies/primitives.py
scrapontologies/parsers/__init__.py
scrapontologies/parsers/base_parser.py
scrapontologies/parsers/pdf_parser.py
scrapontologies/parsers/prompts.py
scrapontologies/renderers/__init__.py
scrapontologies/renderers/base.py
scrapontologies/renderers/pyecharts_renderer.py
scrapontologies-1.1.0.dist-info/METADATA
scrapontologies-1.1.0.dist-info/WHEEL
scrapontologies-1.1.0.dist-info/licenses/LICENSE
scrapontologies-1.1.0.dist-info/RECORD
