Metadata-Version: 2.3
Name: scrapontologies
Version: 1.1.0
Summary: Library for extracting schemas and building ontologies from documents using LLM
Author-email: Lorenzo Padoan <lorenzo.padoan977@gmail.com>, Marco Vinciguerra <mvincig11@gmail.com>, Marco Perini <perinim.98@gmail.com>
License-Expression: MIT
License-File: LICENSE
Keywords: ai,artificial intelligence,documents,gpt,graph,knowledge graph,langchain,machine learning,natural language processing,nlp,ontologies,openai,rag,scrape_schema,scrapegraph,scrapegraphai,scraping,structured data,unstructured data,web scraping,web scraping library,web scraping tool,webscraping
Classifier: Intended Audience :: Developers
Classifier: Operating System :: OS Independent
Classifier: Programming Language :: Python :: 3
Classifier: Topic :: Software Development :: Libraries :: Python Modules
Requires-Python: <4.0,>=3.9
Requires-Dist: certifi>=2024.7.4
Requires-Dist: charset-normalizer>=3.3.2
Requires-Dist: idna>=3.8
Requires-Dist: langchain-anthropic>=0.2.3
Requires-Dist: langchain-core>=0.3.10
Requires-Dist: langchain-google-genai>=2.0.1
Requires-Dist: langchain-google-vertexai>=2.0.5
Requires-Dist: langchain-ollama>=0.2.0
Requires-Dist: langchain-openai>=0.2.2
Requires-Dist: langchain>=0.3.0
Requires-Dist: langgraph>=0.2.31
Requires-Dist: neo4j>=5.25.0
Requires-Dist: pillow>=10.4.0
Requires-Dist: psycopg2>=2.9.9
Requires-Dist: python-dotenv>=1.0.1
Requires-Dist: requests>=2.32.3
Requires-Dist: urllib3>=2.2.2
Provides-Extra: docs
Requires-Dist: furo>=2024.5.6; extra == 'docs'
Requires-Dist: sphinx>=6.0; extra == 'docs'
Provides-Extra: renderers
Requires-Dist: pyecharts>=2.0.6; extra == 'renderers'
